python_docs_theme_lucit/__init__.py
python_docs_theme_lucit/github.html
python_docs_theme_lucit/layout.html
python_docs_theme_lucit/searchbox.html
python_docs_theme_lucit/theme.conf
python_docs_theme_lucit/backup/footerdonate.html
python_docs_theme_lucit/backup/layout.html
python_docs_theme_lucit/orig/github.html
python_docs_theme_lucit/orig/layout.html
python_docs_theme_lucit/orig/searchbox.html
python_docs_theme_lucit/orig/theme.conf
python_docs_theme_lucit/orig/static/copybutton.js
python_docs_theme_lucit/orig/static/github-logo.png
python_docs_theme_lucit/orig/static/lucit.png
python_docs_theme_lucit/orig/static/py.png
python_docs_theme_lucit/orig/static/pydoctheme.css
python_docs_theme_lucit/orig/static/sidebar.js
python_docs_theme_lucit/static/basic.css
python_docs_theme_lucit/static/caret-down.svg
python_docs_theme_lucit/static/classic.css
python_docs_theme_lucit/static/copybutton.js
python_docs_theme_lucit/static/default.css
python_docs_theme_lucit/static/doctools.js
python_docs_theme_lucit/static/documentation_options.js
python_docs_theme_lucit/static/file.png
python_docs_theme_lucit/static/github-logo.png
python_docs_theme_lucit/static/icons8-facebook-20.png
python_docs_theme_lucit/static/icons8-github-20.png
python_docs_theme_lucit/static/icons8-linkedin-20.png
python_docs_theme_lucit/static/icons8-medium-monogram-20.png
python_docs_theme_lucit/static/icons8-twitter-20.png
python_docs_theme_lucit/static/icons8-xing-20.png
python_docs_theme_lucit/static/icons8-youtube-20.png
python_docs_theme_lucit/static/jquery-3.5.1.js
python_docs_theme_lucit/static/jquery.js
python_docs_theme_lucit/static/language_data.js
python_docs_theme_lucit/static/lucit.png
python_docs_theme_lucit/static/menu.js
python_docs_theme_lucit/static/minus.png
python_docs_theme_lucit/static/plus.png
python_docs_theme_lucit/static/py.png
python_docs_theme_lucit/static/py.svg
python_docs_theme_lucit/static/pydoctheme.css
python_docs_theme_lucit/static/pygments.css
python_docs_theme_lucit-1.6.2.dist-info/entry_points.txt
python_docs_theme_lucit-1.6.2.dist-info/licenses/LICENSE
python_docs_theme_lucit-1.6.2.dist-info/WHEEL
python_docs_theme_lucit-1.6.2.dist-info/METADATA
python_docs_theme_lucit-1.6.2.dist-info/RECORD
