Metadata-Version: 2.4
Name: python-docs-theme-lucit
Version: 1.6.2
Summary: The Sphinx theme for the CPython docs and related projects
Author-email: LUCIT <info@lucit.tech>
Requires-Python: >=3.8
Classifier: Development Status :: 5 - Production/Stable
Classifier: Framework :: Sphinx :: Theme
Classifier: Intended Audience :: Developers
Classifier: License :: OSI Approved :: Python Software Foundation License
Classifier: Operating System :: OS Independent
Classifier: Topic :: Documentation
Classifier: Topic :: Software Development :: Documentation
Classifier: Programming Language :: Python
Classifier: Programming Language :: Python :: 3
Classifier: Programming Language :: Python :: 3.8
Classifier: Programming Language :: Python :: 3.9
Classifier: Programming Language :: Python :: 3.10
Classifier: Programming Language :: Python :: 3.11
Classifier: Programming Language :: Python :: 3.12
Classifier: Programming Language :: Python :: 3.13
License-File: LICENSE
Project-URL: Code, https://github.com/LUCIT-Systems-and-Development/python-docs-theme-lucit
Project-URL: Download, https://pypi.org/project/python-docs-theme-lucit/
Project-URL: Homepage, https://github.com/LUCIT-Systems-and-Development/python-docs-theme-lucit
Project-URL: Issue tracker, https://github.com/LUCIT-Systems-and-Development/python-docs-theme-lucit/issues
